instMEM/instMEM.v
module instMEM (clk, reset, address, instRead, data_out, opcode, dest, source1, source2, imm);
input clk, reset, instRead;
input [7:0] address;
output reg [24:0] data_out;
output reg [4:0] opcode;
output reg [3:0] dest;
output reg [3:0] source1;
output reg [3:0] source2;
output reg [7:0] imm;

// reg [24:0] instmemory [0:255];
reg [24:0] instmemory [0:4]; // For Testing

always @(posedge clk)
begin
    if(reset == 1'b1)
        begin
            data_out <= 0;
            opcode <= 0;
            dest <= 0;
            source1 <= 0;
            source2 <= 0;
            imm <= 0;
        end
    else   
        begin
            if(instRead == 1'b1)
                begin
                    data_out <= instmemory[address] [24:0];
                    opcode <= instmemory[address] [24:20];
                    dest <= instmemory[address] [19:16];
                    source1 <= instmemory[address] [15:12];
                    source2 <= instmemory[address] [11:8];
                    imm <= instmemory[address] [7:0];
                end
        end
end

initial
    begin
        $readmemb("inst_mem_file.dat", instmemory);  
    end

endmodule

instMEM/instMEM_tb.v
module instMem_tb();
  reg clk, reset, instRead;
  reg [7:0] address;
  wire [24:0] data_out;
  wire [4:0] opcode;
  wire [3:0] dest;
  wire [3:0] source1;
  wire [3:0] source2;
  wire [7:0] imm;

  // Instantiate the Module
  instMEM inst1 (
    .clk(clk), 
    .reset(reset), 
    .address(address), 
    .instRead(instRead), 
    .data_out(data_out), 
    .opcode(opcode), 
    .dest(dest), 
    .source1(source1), 
    .source2(source2), 
    .imm(imm)
  );

  integer i;

  // Generate Clock
  always #5 clk = ~clk;

  initial begin
    $dumpfile("Wavedump.vcd");
    $dumpvars;

    // Initialize Signals
    clk = 0;
    reset = 1;
    instRead = 0;
    address = 0;

    // Reset Phase
    #10 reset = 0;
    instRead = 1;

    // Read Instructions and Display
    for (i = 0; i < 5; i = i + 1) begin
      address = i;
      #10; // Allow time for data to settle
      $display("Address=%h Data Out=%b Opcode=%b Dest=%b Src1=%b Src2=%b Imm=%b",
               address, data_out, opcode, dest, source1, source2, imm);
    end

    #20 $finish;
  end
endmodule

instMEM/Wavedump.vcd
$date
	Fri Mar 28 13:02:30 2025
$end
$version
	Icarus Verilog
$end
$timescale
	1s
$end
$scope module instMem_tb $end
$var wire 4 ! source2 [3:0] $end
$var wire 4 " source1 [3:0] $end
$var wire 5 # opcode [4:0] $end
$var wire 8 $ imm [7:0] $end
$var wire 4 % dest [3:0] $end
$var wire 25 & data_out [24:0] $end
$var reg 8 ' address [7:0] $end
$var reg 1 ( clk $end
$var reg 1 ) instRead $end
$var reg 1 * reset $end
$var integer 32 + i [31:0] $end
$scope module inst1 $end
$var wire 8 , address [7:0] $end
$var wire 1 ( clk $end
$var wire 1 ) instRead $end
$var wire 1 * reset $end
$var reg 25 - data_out [24:0] $end
$var reg 4 . dest [3:0] $end
$var reg 8 / imm [7:0] $end
$var reg 5 0 opcode [4:0] $end
$var reg 4 1 source1 [3:0] $end
$var reg 4 2 source2 [3:0] $end
$upscope $end
$upscope $end
$enddefinitions $end
$comment Show the parameter values. $end
$dumpall
$end
#0
$dumpvars
bx 2
bx 1
bx 0
bx /
bx .
bx -
b0 ,
bx +
1*
0)
0(
b0 '
bx &
bx %
bx $
bx #
bx "
bx !
$end
#5
b0 $
b0 /
b0 !
b0 2
b0 "
b0 1
b0 %
b0 .
b0 #
b0 0
b0 &
b0 -
1(
#10
0(
b0 +
1)
0*
#15
b110 !
b110 2
b10 "
b10 1
b10 %
b10 .
b1 #
b1 0
b100100010011000000000 &
b100100010011000000000 -
1(
#20
0(
b1 '
b1 ,
b1 +
#25
b10 !
b10 2
b110 "
b110 1
b100 %
b100 .
b10 #
b10 0
b1001000110001000000000 &
b1001000110001000000000 -
1(
#30
0(
b10 '
b10 ,
b10 +
#35
b110 !
b110 2
b100 "
b100 1
b101 %
b101 .
b11 #
b11 0
b1101010100011000000000 &
b1101010100011000000000 -
1(
#40
0(
b11 '
b11 ,
b11 +
#45
b1010000 $
b1010000 /
b0 !
b0 2
b0 "
b0 1
b110 %
b110 .
b100 #
b100 0
b10001100000000001010000 &
b10001100000000001010000 -
1(
#50
0(
b100 '
b100 ,
b100 +
#55
b11111 $
b11111 /
b111 %
b111 .
b101 #
b101 0
b10101110000000000011111 &
b10101110000000000011111 -
1(
#60
0(
b101 +
